gradion/__init__.py
gradion/executor/__init__.py
gradion/executor/__main__.py
gradion/executor/client.py
gradion/executor/config/default/dependencies.txt
gradion/executor/config/default/environment.yml
gradion/executor/config/default/pyproject.toml
gradion/executor/container.py
gradion/executor/docker/Dockerfile
gradion/executor/scripts/cleanup.sh
gradion/executor/scripts/server.sh
gradion_executor-0.1.2.dist-info/LICENSE
gradion_executor-0.1.2.dist-info/METADATA
gradion_executor-0.1.2.dist-info/WHEEL
gradion_executor-0.1.2.dist-info/RECORD
