Metadata-Version: 2.1
Name: gradion-executor
Version: 0.1.2
Summary: Gradion AI Code Execution Container
Home-page: https://github.com/gradion-ai/executor
License: Apache-2.0
Author: Martin Krasser
Author-email: martin@gradion.ai
Requires-Python: >=3.10,<3.13
Classifier: License :: OSI Approved :: Apache Software License
Classifier: Programming Language :: Python :: 3
Classifier: Programming Language :: Python :: 3.10
Classifier: Programming Language :: Python :: 3.11
Classifier: Programming Language :: Python :: 3.12
Requires-Dist: aiodocker (>=0.23.0,<0.24.0)
Requires-Dist: aiofiles (>=24.1,<25.0)
Requires-Dist: aiohttp (>=3.10,<4.0)
Requires-Dist: pillow (>=11.0,<12.0)
Requires-Dist: tornado (>=6.4,<7.0)
Requires-Dist: typer (>=0.12.5,<0.13.0)
